{
    "initialAllocation": [
        {
            "module_name": "0_1",
            "app": "0",
            "id_resource": 75
        },
        {
            "module_name": "0_1",
            "app": "0",
            "id_resource": 125
        },
        {
            "module_name": "0_2",
            "app": "0",
            "id_resource": 91
        },
        {
            "module_name": "0_3",
            "app": "0",
            "id_resource": 70
        },
        {
            "module_name": "0_4",
            "app": "0",
            "id_resource": 77
        },
        {
            "module_name": "0_5",
            "app": "0",
            "id_resource": 86
        },
        {
            "module_name": "0_6",
            "app": "0",
            "id_resource": 132
        },
        {
            "module_name": "0_7",
            "app": "0",
            "id_resource": 83
        },
        {
            "module_name": "0_8",
            "app": "0",
            "id_resource": 43
        },
        {
            "module_name": "0_8",
            "app": "0",
            "id_resource": 198
        },
        {
            "module_name": "0_9",
            "app": "0",
            "id_resource": 99
        },
        {
            "module_name": "0_10",
            "app": "0",
            "id_resource": 10
        },
        {
            "module_name": "0_10",
            "app": "0",
            "id_resource": 152
        },
        {
            "module_name": "0_11",
            "app": "0",
            "id_resource": 15
        },
        {
            "module_name": "0_11",
            "app": "0",
            "id_resource": 181
        },
        {
            "module_name": "0_12",
            "app": "0",
            "id_resource": 177
        },
        {
            "module_name": "0_12",
            "app": "0",
            "id_resource": 124
        },
        {
            "module_name": "0_13",
            "app": "0",
            "id_resource": 34
        },
        {
            "module_name": "0_14",
            "app": "0",
            "id_resource": 14
        },
        {
            "module_name": "0_15",
            "app": "0",
            "id_resource": 135
        },
        {
            "module_name": "0_16",
            "app": "0",
            "id_resource": 0
        },
        {
            "module_name": "0_17",
            "app": "0",
            "id_resource": 8
        },
        {
            "module_name": "0_18",
            "app": "0",
            "id_resource": 4
        },
        {
            "module_name": "1_20",
            "app": "1",
            "id_resource": 26
        },
        {
            "module_name": "1_20",
            "app": "1",
            "id_resource": 10
        },
        {
            "module_name": "1_21",
            "app": "1",
            "id_resource": 0
        },
        {
            "module_name": "1_22",
            "app": "1",
            "id_resource": 5
        },
        {
            "module_name": "1_22",
            "app": "1",
            "id_resource": 38
        },
        {
            "module_name": "1_23",
            "app": "1",
            "id_resource": 68
        },
        {
            "module_name": "1_23",
            "app": "1",
            "id_resource": 168
        },
        {
            "module_name": "1_24",
            "app": "1",
            "id_resource": 167
        },
        {
            "module_name": "1_25",
            "app": "1",
            "id_resource": 36
        },
        {
            "module_name": "1_25",
            "app": "1",
            "id_resource": 189
        },
        {
            "module_name": "1_26",
            "app": "1",
            "id_resource": 64
        },
        {
            "module_name": "1_27",
            "app": "1",
            "id_resource": 37
        },
        {
            "module_name": "1_28",
            "app": "1",
            "id_resource": 186
        },
        {
            "module_name": "1_28",
            "app": "1",
            "id_resource": 197
        },
        {
            "module_name": "1_29",
            "app": "1",
            "id_resource": 35
        },
        {
            "module_name": "1_30",
            "app": "1",
            "id_resource": 107
        },
        {
            "module_name": "1_30",
            "app": "1",
            "id_resource": 21
        },
        {
            "module_name": "1_30",
            "app": "1",
            "id_resource": 58
        },
        {
            "module_name": "1_30",
            "app": "1",
            "id_resource": 145
        },
        {
            "module_name": "1_31",
            "app": "1",
            "id_resource": 87
        },
        {
            "module_name": "1_32",
            "app": "1",
            "id_resource": 171
        },
        {
            "module_name": "1_32",
            "app": "1",
            "id_resource": 199
        },
        {
            "module_name": "1_33",
            "app": "1",
            "id_resource": 7
        },
        {
            "module_name": "1_33",
            "app": "1",
            "id_resource": 94
        },
        {
            "module_name": "1_33",
            "app": "1",
            "id_resource": 168
        },
        {
            "module_name": "1_34",
            "app": "1",
            "id_resource": 7
        },
        {
            "module_name": "1_34",
            "app": "1",
            "id_resource": 178
        },
        {
            "module_name": "1_35",
            "app": "1",
            "id_resource": 67
        },
        {
            "module_name": "1_36",
            "app": "1",
            "id_resource": 35
        },
        {
            "module_name": "1_37",
            "app": "1",
            "id_resource": 167
        },
        {
            "module_name": "1_37",
            "app": "1",
            "id_resource": 139
        },
        {
            "module_name": "2_39",
            "app": "2",
            "id_resource": 14
        },
        {
            "module_name": "2_39",
            "app": "2",
            "id_resource": 49
        },
        {
            "module_name": "2_40",
            "app": "2",
            "id_resource": 6
        },
        {
            "module_name": "2_40",
            "app": "2",
            "id_resource": 123
        },
        {
            "module_name": "2_41",
            "app": "2",
            "id_resource": 35
        },
        {
            "module_name": "2_41",
            "app": "2",
            "id_resource": 117
        },
        {
            "module_name": "2_42",
            "app": "2",
            "id_resource": 60
        },
        {
            "module_name": "2_42",
            "app": "2",
            "id_resource": 182
        },
        {
            "module_name": "2_42",
            "app": "2",
            "id_resource": 131
        },
        {
            "module_name": "2_43",
            "app": "2",
            "id_resource": 84
        },
        {
            "module_name": "2_44",
            "app": "2",
            "id_resource": 13
        },
        {
            "module_name": "2_45",
            "app": "2",
            "id_resource": 89
        },
        {
            "module_name": "2_46",
            "app": "2",
            "id_resource": 6
        },
        {
            "module_name": "2_46",
            "app": "2",
            "id_resource": 117
        },
        {
            "module_name": "2_47",
            "app": "2",
            "id_resource": 38
        },
        {
            "module_name": "2_48",
            "app": "2",
            "id_resource": 160
        },
        {
            "module_name": "2_49",
            "app": "2",
            "id_resource": 6
        },
        {
            "module_name": "2_50",
            "app": "2",
            "id_resource": 170
        },
        {
            "module_name": "2_50",
            "app": "2",
            "id_resource": 196
        },
        {
            "module_name": "2_51",
            "app": "2",
            "id_resource": 50
        },
        {
            "module_name": "2_51",
            "app": "2",
            "id_resource": 99
        },
        {
            "module_name": "2_51",
            "app": "2",
            "id_resource": 186
        },
        {
            "module_name": "2_51",
            "app": "2",
            "id_resource": 164
        },
        {
            "module_name": "3_53",
            "app": "3",
            "id_resource": 6
        },
        {
            "module_name": "3_54",
            "app": "3",
            "id_resource": 151
        },
        {
            "module_name": "3_55",
            "app": "3",
            "id_resource": 72
        },
        {
            "module_name": "3_55",
            "app": "3",
            "id_resource": 154
        },
        {
            "module_name": "3_56",
            "app": "3",
            "id_resource": 6
        },
        {
            "module_name": "3_56",
            "app": "3",
            "id_resource": 19
        },
        {
            "module_name": "3_56",
            "app": "3",
            "id_resource": 69
        },
        {
            "module_name": "3_57",
            "app": "3",
            "id_resource": 20
        },
        {
            "module_name": "3_57",
            "app": "3",
            "id_resource": 142
        },
        {
            "module_name": "3_58",
            "app": "3",
            "id_resource": 47
        },
        {
            "module_name": "3_58",
            "app": "3",
            "id_resource": 130
        },
        {
            "module_name": "3_58",
            "app": "3",
            "id_resource": 155
        },
        {
            "module_name": "3_59",
            "app": "3",
            "id_resource": 92
        },
        {
            "module_name": "3_59",
            "app": "3",
            "id_resource": 146
        },
        {
            "module_name": "3_60",
            "app": "3",
            "id_resource": 63
        },
        {
            "module_name": "3_60",
            "app": "3",
            "id_resource": 37
        },
        {
            "module_name": "3_60",
            "app": "3",
            "id_resource": 123
        },
        {
            "module_name": "3_61",
            "app": "3",
            "id_resource": 10
        },
        {
            "module_name": "3_62",
            "app": "3",
            "id_resource": 79
        },
        {
            "module_name": "3_62",
            "app": "3",
            "id_resource": 146
        },
        {
            "module_name": "4_63",
            "app": "4",
            "id_resource": 195
        },
        {
            "module_name": "4_64",
            "app": "4",
            "id_resource": 97
        },
        {
            "module_name": "4_64",
            "app": "4",
            "id_resource": 190
        },
        {
            "module_name": "4_65",
            "app": "4",
            "id_resource": 189
        },
        {
            "module_name": "4_66",
            "app": "4",
            "id_resource": 170
        },
        {
            "module_name": "4_67",
            "app": "4",
            "id_resource": 36
        },
        {
            "module_name": "4_67",
            "app": "4",
            "id_resource": 126
        },
        {
            "module_name": "4_67",
            "app": "4",
            "id_resource": 128
        },
        {
            "module_name": "4_68",
            "app": "4",
            "id_resource": 24
        },
        {
            "module_name": "4_69",
            "app": "4",
            "id_resource": 15
        },
        {
            "module_name": "4_70",
            "app": "4",
            "id_resource": 12
        },
        {
            "module_name": "4_70",
            "app": "4",
            "id_resource": 150
        },
        {
            "module_name": "4_70",
            "app": "4",
            "id_resource": 174
        },
        {
            "module_name": "4_71",
            "app": "4",
            "id_resource": 15
        },
        {
            "module_name": "4_72",
            "app": "4",
            "id_resource": 32
        },
        {
            "module_name": "4_72",
            "app": "4",
            "id_resource": 172
        },
        {
            "module_name": "4_72",
            "app": "4",
            "id_resource": 152
        },
        {
            "module_name": "4_72",
            "app": "4",
            "id_resource": 199
        },
        {
            "module_name": "4_73",
            "app": "4",
            "id_resource": 77
        },
        {
            "module_name": "4_73",
            "app": "4",
            "id_resource": 199
        },
        {
            "module_name": "4_74",
            "app": "4",
            "id_resource": 37
        },
        {
            "module_name": "4_74",
            "app": "4",
            "id_resource": 141
        },
        {
            "module_name": "5_76",
            "app": "5",
            "id_resource": 46
        },
        {
            "module_name": "5_77",
            "app": "5",
            "id_resource": 72
        },
        {
            "module_name": "5_77",
            "app": "5",
            "id_resource": 83
        },
        {
            "module_name": "5_77",
            "app": "5",
            "id_resource": 193
        },
        {
            "module_name": "5_78",
            "app": "5",
            "id_resource": 1
        },
        {
            "module_name": "5_78",
            "app": "5",
            "id_resource": 168
        },
        {
            "module_name": "5_79",
            "app": "5",
            "id_resource": 180
        },
        {
            "module_name": "5_79",
            "app": "5",
            "id_resource": 181
        },
        {
            "module_name": "6_81",
            "app": "6",
            "id_resource": 12
        },
        {
            "module_name": "6_81",
            "app": "6",
            "id_resource": 127
        },
        {
            "module_name": "6_82",
            "app": "6",
            "id_resource": 17
        },
        {
            "module_name": "6_82",
            "app": "6",
            "id_resource": 74
        },
        {
            "module_name": "6_82",
            "app": "6",
            "id_resource": 132
        },
        {
            "module_name": "6_83",
            "app": "6",
            "id_resource": 4
        },
        {
            "module_name": "6_83",
            "app": "6",
            "id_resource": 70
        },
        {
            "module_name": "6_83",
            "app": "6",
            "id_resource": 98
        },
        {
            "module_name": "6_84",
            "app": "6",
            "id_resource": 0
        },
        {
            "module_name": "6_84",
            "app": "6",
            "id_resource": 158
        },
        {
            "module_name": "6_85",
            "app": "6",
            "id_resource": 11
        },
        {
            "module_name": "6_85",
            "app": "6",
            "id_resource": 57
        },
        {
            "module_name": "6_86",
            "app": "6",
            "id_resource": 111
        },
        {
            "module_name": "6_86",
            "app": "6",
            "id_resource": 84
        },
        {
            "module_name": "6_86",
            "app": "6",
            "id_resource": 192
        },
        {
            "module_name": "6_87",
            "app": "6",
            "id_resource": 103
        },
        {
            "module_name": "6_88",
            "app": "6",
            "id_resource": 177
        },
        {
            "module_name": "6_88",
            "app": "6",
            "id_resource": 169
        },
        {
            "module_name": "6_89",
            "app": "6",
            "id_resource": 70
        },
        {
            "module_name": "6_90",
            "app": "6",
            "id_resource": 31
        },
        {
            "module_name": "6_91",
            "app": "6",
            "id_resource": 41
        },
        {
            "module_name": "6_91",
            "app": "6",
            "id_resource": 36
        },
        {
            "module_name": "6_92",
            "app": "6",
            "id_resource": 41
        },
        {
            "module_name": "6_93",
            "app": "6",
            "id_resource": 20
        },
        {
            "module_name": "6_94",
            "app": "6",
            "id_resource": 85
        },
        {
            "module_name": "6_95",
            "app": "6",
            "id_resource": 13
        },
        {
            "module_name": "6_96",
            "app": "6",
            "id_resource": 20
        },
        {
            "module_name": "6_97",
            "app": "6",
            "id_resource": 165
        },
        {
            "module_name": "7_99",
            "app": "7",
            "id_resource": 97
        },
        {
            "module_name": "7_100",
            "app": "7",
            "id_resource": 56
        },
        {
            "module_name": "7_101",
            "app": "7",
            "id_resource": 38
        },
        {
            "module_name": "7_101",
            "app": "7",
            "id_resource": 185
        },
        {
            "module_name": "7_102",
            "app": "7",
            "id_resource": 176
        },
        {
            "module_name": "7_102",
            "app": "7",
            "id_resource": 164
        },
        {
            "module_name": "7_103",
            "app": "7",
            "id_resource": 125
        },
        {
            "module_name": "7_104",
            "app": "7",
            "id_resource": 75
        },
        {
            "module_name": "7_104",
            "app": "7",
            "id_resource": 30
        },
        {
            "module_name": "7_105",
            "app": "7",
            "id_resource": 6
        },
        {
            "module_name": "7_106",
            "app": "7",
            "id_resource": 61
        },
        {
            "module_name": "7_106",
            "app": "7",
            "id_resource": 23
        },
        {
            "module_name": "7_106",
            "app": "7",
            "id_resource": 119
        },
        {
            "module_name": "7_107",
            "app": "7",
            "id_resource": 18
        },
        {
            "module_name": "7_107",
            "app": "7",
            "id_resource": 142
        },
        {
            "module_name": "7_107",
            "app": "7",
            "id_resource": 137
        },
        {
            "module_name": "7_108",
            "app": "7",
            "id_resource": 55
        },
        {
            "module_name": "7_109",
            "app": "7",
            "id_resource": 111
        },
        {
            "module_name": "7_109",
            "app": "7",
            "id_resource": 172
        },
        {
            "module_name": "7_109",
            "app": "7",
            "id_resource": 165
        },
        {
            "module_name": "7_109",
            "app": "7",
            "id_resource": 146
        },
        {
            "module_name": "7_110",
            "app": "7",
            "id_resource": 76
        },
        {
            "module_name": "7_111",
            "app": "7",
            "id_resource": 0
        },
        {
            "module_name": "7_111",
            "app": "7",
            "id_resource": 108
        },
        {
            "module_name": "7_112",
            "app": "7",
            "id_resource": 0
        },
        {
            "module_name": "7_112",
            "app": "7",
            "id_resource": 154
        },
        {
            "module_name": "7_113",
            "app": "7",
            "id_resource": 24
        },
        {
            "module_name": "7_113",
            "app": "7",
            "id_resource": 130
        },
        {
            "module_name": "7_113",
            "app": "7",
            "id_resource": 138
        },
        {
            "module_name": "7_113",
            "app": "7",
            "id_resource": 157
        },
        {
            "module_name": "8_115",
            "app": "8",
            "id_resource": 2
        },
        {
            "module_name": "8_116",
            "app": "8",
            "id_resource": 41
        },
        {
            "module_name": "8_116",
            "app": "8",
            "id_resource": 144
        },
        {
            "module_name": "8_117",
            "app": "8",
            "id_resource": 98
        },
        {
            "module_name": "8_117",
            "app": "8",
            "id_resource": 69
        },
        {
            "module_name": "8_117",
            "app": "8",
            "id_resource": 114
        },
        {
            "module_name": "8_118",
            "app": "8",
            "id_resource": 27
        },
        {
            "module_name": "8_118",
            "app": "8",
            "id_resource": 143
        },
        {
            "module_name": "8_118",
            "app": "8",
            "id_resource": 163
        },
        {
            "module_name": "8_118",
            "app": "8",
            "id_resource": 174
        },
        {
            "module_name": "8_119",
            "app": "8",
            "id_resource": 96
        },
        {
            "module_name": "8_119",
            "app": "8",
            "id_resource": 192
        },
        {
            "module_name": "8_120",
            "app": "8",
            "id_resource": 41
        },
        {
            "module_name": "8_120",
            "app": "8",
            "id_resource": 87
        },
        {
            "module_name": "8_120",
            "app": "8",
            "id_resource": 101
        },
        {
            "module_name": "8_121",
            "app": "8",
            "id_resource": 41
        },
        {
            "module_name": "8_122",
            "app": "8",
            "id_resource": 20
        },
        {
            "module_name": "8_122",
            "app": "8",
            "id_resource": 37
        },
        {
            "module_name": "8_123",
            "app": "8",
            "id_resource": 105
        },
        {
            "module_name": "8_124",
            "app": "8",
            "id_resource": 95
        },
        {
            "module_name": "8_124",
            "app": "8",
            "id_resource": 115
        },
        {
            "module_name": "8_124",
            "app": "8",
            "id_resource": 146
        },
        {
            "module_name": "8_125",
            "app": "8",
            "id_resource": 191
        },
        {
            "module_name": "8_126",
            "app": "8",
            "id_resource": 187
        },
        {
            "module_name": "8_126",
            "app": "8",
            "id_resource": 125
        },
        {
            "module_name": "8_127",
            "app": "8",
            "id_resource": 32
        },
        {
            "module_name": "9_129",
            "app": "9",
            "id_resource": 41
        },
        {
            "module_name": "9_129",
            "app": "9",
            "id_resource": 57
        },
        {
            "module_name": "9_130",
            "app": "9",
            "id_resource": 188
        },
        {
            "module_name": "9_130",
            "app": "9",
            "id_resource": 162
        },
        {
            "module_name": "9_131",
            "app": "9",
            "id_resource": 123
        },
        {
            "module_name": "9_132",
            "app": "9",
            "id_resource": 56
        },
        {
            "module_name": "9_133",
            "app": "9",
            "id_resource": 74
        },
        {
            "module_name": "9_133",
            "app": "9",
            "id_resource": 161
        },
        {
            "module_name": "9_134",
            "app": "9",
            "id_resource": 5
        },
        {
            "module_name": "9_135",
            "app": "9",
            "id_resource": 76
        },
        {
            "module_name": "9_135",
            "app": "9",
            "id_resource": 126
        },
        {
            "module_name": "9_136",
            "app": "9",
            "id_resource": 188
        },
        {
            "module_name": "9_136",
            "app": "9",
            "id_resource": 174
        },
        {
            "module_name": "9_137",
            "app": "9",
            "id_resource": 0
        },
        {
            "module_name": "9_138",
            "app": "9",
            "id_resource": 15
        },
        {
            "module_name": "9_139",
            "app": "9",
            "id_resource": 3
        },
        {
            "module_name": "9_139",
            "app": "9",
            "id_resource": 95
        },
        {
            "module_name": "9_140",
            "app": "9",
            "id_resource": 6
        },
        {
            "module_name": "9_141",
            "app": "9",
            "id_resource": 108
        },
        {
            "module_name": "9_141",
            "app": "9",
            "id_resource": 66
        },
        {
            "module_name": "9_142",
            "app": "9",
            "id_resource": 62
        },
        {
            "module_name": "9_142",
            "app": "9",
            "id_resource": 155
        },
        {
            "module_name": "9_142",
            "app": "9",
            "id_resource": 114
        },
        {
            "module_name": "10_143",
            "app": "10",
            "id_resource": 199
        },
        {
            "module_name": "10_144",
            "app": "10",
            "id_resource": 51
        },
        {
            "module_name": "10_144",
            "app": "10",
            "id_resource": 95
        },
        {
            "module_name": "10_144",
            "app": "10",
            "id_resource": 129
        },
        {
            "module_name": "11_146",
            "app": "11",
            "id_resource": 44
        },
        {
            "module_name": "11_147",
            "app": "11",
            "id_resource": 72
        },
        {
            "module_name": "11_147",
            "app": "11",
            "id_resource": 31
        },
        {
            "module_name": "11_148",
            "app": "11",
            "id_resource": 47
        },
        {
            "module_name": "12_150",
            "app": "12",
            "id_resource": 1
        },
        {
            "module_name": "12_150",
            "app": "12",
            "id_resource": 107
        },
        {
            "module_name": "12_151",
            "app": "12",
            "id_resource": 83
        },
        {
            "module_name": "12_151",
            "app": "12",
            "id_resource": 150
        },
        {
            "module_name": "12_152",
            "app": "12",
            "id_resource": 68
        },
        {
            "module_name": "12_152",
            "app": "12",
            "id_resource": 138
        },
        {
            "module_name": "12_153",
            "app": "12",
            "id_resource": 26
        },
        {
            "module_name": "12_153",
            "app": "12",
            "id_resource": 42
        },
        {
            "module_name": "12_154",
            "app": "12",
            "id_resource": 76
        },
        {
            "module_name": "12_155",
            "app": "12",
            "id_resource": 195
        },
        {
            "module_name": "12_155",
            "app": "12",
            "id_resource": 196
        },
        {
            "module_name": "12_156",
            "app": "12",
            "id_resource": 15
        },
        {
            "module_name": "12_156",
            "app": "12",
            "id_resource": 25
        },
        {
            "module_name": "12_157",
            "app": "12",
            "id_resource": 2
        },
        {
            "module_name": "12_158",
            "app": "12",
            "id_resource": 61
        },
        {
            "module_name": "12_158",
            "app": "12",
            "id_resource": 31
        },
        {
            "module_name": "12_158",
            "app": "12",
            "id_resource": 186
        },
        {
            "module_name": "12_159",
            "app": "12",
            "id_resource": 82
        },
        {
            "module_name": "12_159",
            "app": "12",
            "id_resource": 42
        },
        {
            "module_name": "12_159",
            "app": "12",
            "id_resource": 118
        },
        {
            "module_name": "12_160",
            "app": "12",
            "id_resource": 111
        },
        {
            "module_name": "12_161",
            "app": "12",
            "id_resource": 22
        },
        {
            "module_name": "12_161",
            "app": "12",
            "id_resource": 162
        },
        {
            "module_name": "12_162",
            "app": "12",
            "id_resource": 92
        },
        {
            "module_name": "12_162",
            "app": "12",
            "id_resource": 60
        },
        {
            "module_name": "12_163",
            "app": "12",
            "id_resource": 4
        },
        {
            "module_name": "12_164",
            "app": "12",
            "id_resource": 181
        },
        {
            "module_name": "12_164",
            "app": "12",
            "id_resource": 199
        },
        {
            "module_name": "12_165",
            "app": "12",
            "id_resource": 64
        },
        {
            "module_name": "12_165",
            "app": "12",
            "id_resource": 74
        },
        {
            "module_name": "12_166",
            "app": "12",
            "id_resource": 120
        },
        {
            "module_name": "12_167",
            "app": "12",
            "id_resource": 86
        },
        {
            "module_name": "12_167",
            "app": "12",
            "id_resource": 38
        },
        {
            "module_name": "13_169",
            "app": "13",
            "id_resource": 28
        },
        {
            "module_name": "13_170",
            "app": "13",
            "id_resource": 32
        },
        {
            "module_name": "13_171",
            "app": "13",
            "id_resource": 19
        },
        {
            "module_name": "13_171",
            "app": "13",
            "id_resource": 105
        },
        {
            "module_name": "13_171",
            "app": "13",
            "id_resource": 128
        },
        {
            "module_name": "13_172",
            "app": "13",
            "id_resource": 162
        },
        {
            "module_name": "13_173",
            "app": "13",
            "id_resource": 25
        },
        {
            "module_name": "13_173",
            "app": "13",
            "id_resource": 130
        },
        {
            "module_name": "13_173",
            "app": "13",
            "id_resource": 190
        },
        {
            "module_name": "13_174",
            "app": "13",
            "id_resource": 69
        },
        {
            "module_name": "13_174",
            "app": "13",
            "id_resource": 153
        },
        {
            "module_name": "13_174",
            "app": "13",
            "id_resource": 156
        },
        {
            "module_name": "13_175",
            "app": "13",
            "id_resource": 179
        },
        {
            "module_name": "13_175",
            "app": "13",
            "id_resource": 144
        },
        {
            "module_name": "14_176",
            "app": "14",
            "id_resource": 196
        },
        {
            "module_name": "14_177",
            "app": "14",
            "id_resource": 194
        },
        {
            "module_name": "14_178",
            "app": "14",
            "id_resource": 44
        },
        {
            "module_name": "14_178",
            "app": "14",
            "id_resource": 180
        },
        {
            "module_name": "14_179",
            "app": "14",
            "id_resource": 54
        },
        {
            "module_name": "14_179",
            "app": "14",
            "id_resource": 194
        },
        {
            "module_name": "14_180",
            "app": "14",
            "id_resource": 153
        },
        {
            "module_name": "14_181",
            "app": "14",
            "id_resource": 168
        },
        {
            "module_name": "14_182",
            "app": "14",
            "id_resource": 142
        },
        {
            "module_name": "14_182",
            "app": "14",
            "id_resource": 153
        },
        {
            "module_name": "14_183",
            "app": "14",
            "id_resource": 12
        },
        {
            "module_name": "14_184",
            "app": "14",
            "id_resource": 23
        },
        {
            "module_name": "14_184",
            "app": "14",
            "id_resource": 153
        },
        {
            "module_name": "14_184",
            "app": "14",
            "id_resource": 143
        },
        {
            "module_name": "14_185",
            "app": "14",
            "id_resource": 3
        },
        {
            "module_name": "14_185",
            "app": "14",
            "id_resource": 163
        },
        {
            "module_name": "14_186",
            "app": "14",
            "id_resource": 35
        },
        {
            "module_name": "14_186",
            "app": "14",
            "id_resource": 102
        },
        {
            "module_name": "14_186",
            "app": "14",
            "id_resource": 17
        },
        {
            "module_name": "14_187",
            "app": "14",
            "id_resource": 91
        },
        {
            "module_name": "14_187",
            "app": "14",
            "id_resource": 81
        },
        {
            "module_name": "14_188",
            "app": "14",
            "id_resource": 163
        },
        {
            "module_name": "14_189",
            "app": "14",
            "id_resource": 110
        },
        {
            "module_name": "14_189",
            "app": "14",
            "id_resource": 41
        },
        {
            "module_name": "14_189",
            "app": "14",
            "id_resource": 69
        },
        {
            "module_name": "14_189",
            "app": "14",
            "id_resource": 181
        },
        {
            "module_name": "15_190",
            "app": "15",
            "id_resource": 199
        },
        {
            "module_name": "15_191",
            "app": "15",
            "id_resource": 32
        },
        {
            "module_name": "15_192",
            "app": "15",
            "id_resource": 130
        },
        {
            "module_name": "15_193",
            "app": "15",
            "id_resource": 39
        },
        {
            "module_name": "15_194",
            "app": "15",
            "id_resource": 90
        },
        {
            "module_name": "15_194",
            "app": "15",
            "id_resource": 99
        },
        {
            "module_name": "15_195",
            "app": "15",
            "id_resource": 1
        },
        {
            "module_name": "15_195",
            "app": "15",
            "id_resource": 59
        },
        {
            "module_name": "15_195",
            "app": "15",
            "id_resource": 153
        },
        {
            "module_name": "15_195",
            "app": "15",
            "id_resource": 176
        },
        {
            "module_name": "15_196",
            "app": "15",
            "id_resource": 107
        },
        {
            "module_name": "15_196",
            "app": "15",
            "id_resource": 106
        },
        {
            "module_name": "15_197",
            "app": "15",
            "id_resource": 192
        },
        {
            "module_name": "15_197",
            "app": "15",
            "id_resource": 144
        },
        {
            "module_name": "15_198",
            "app": "15",
            "id_resource": 96
        },
        {
            "module_name": "15_199",
            "app": "15",
            "id_resource": 96
        },
        {
            "module_name": "15_199",
            "app": "15",
            "id_resource": 19
        },
        {
            "module_name": "15_200",
            "app": "15",
            "id_resource": 32
        },
        {
            "module_name": "15_201",
            "app": "15",
            "id_resource": 32
        },
        {
            "module_name": "15_201",
            "app": "15",
            "id_resource": 25
        },
        {
            "module_name": "15_202",
            "app": "15",
            "id_resource": 4
        },
        {
            "module_name": "15_202",
            "app": "15",
            "id_resource": 97
        },
        {
            "module_name": "15_203",
            "app": "15",
            "id_resource": 30
        },
        {
            "module_name": "15_204",
            "app": "15",
            "id_resource": 5
        },
        {
            "module_name": "15_204",
            "app": "15",
            "id_resource": 134
        },
        {
            "module_name": "15_204",
            "app": "15",
            "id_resource": 169
        },
        {
            "module_name": "15_205",
            "app": "15",
            "id_resource": 101
        },
        {
            "module_name": "15_205",
            "app": "15",
            "id_resource": 121
        },
        {
            "module_name": "15_206",
            "app": "15",
            "id_resource": 55
        },
        {
            "module_name": "15_206",
            "app": "15",
            "id_resource": 95
        },
        {
            "module_name": "15_206",
            "app": "15",
            "id_resource": 79
        },
        {
            "module_name": "15_206",
            "app": "15",
            "id_resource": 59
        },
        {
            "module_name": "15_206",
            "app": "15",
            "id_resource": 116
        },
        {
            "module_name": "16_208",
            "app": "16",
            "id_resource": 2
        },
        {
            "module_name": "16_209",
            "app": "16",
            "id_resource": 48
        },
        {
            "module_name": "16_210",
            "app": "16",
            "id_resource": 50
        },
        {
            "module_name": "16_210",
            "app": "16",
            "id_resource": 166
        },
        {
            "module_name": "16_210",
            "app": "16",
            "id_resource": 131
        },
        {
            "module_name": "17_212",
            "app": "17",
            "id_resource": 109
        },
        {
            "module_name": "17_212",
            "app": "17",
            "id_resource": 170
        },
        {
            "module_name": "17_212",
            "app": "17",
            "id_resource": 133
        },
        {
            "module_name": "17_213",
            "app": "17",
            "id_resource": 35
        },
        {
            "module_name": "17_213",
            "app": "17",
            "id_resource": 108
        },
        {
            "module_name": "17_213",
            "app": "17",
            "id_resource": 161
        },
        {
            "module_name": "17_214",
            "app": "17",
            "id_resource": 47
        },
        {
            "module_name": "17_214",
            "app": "17",
            "id_resource": 141
        },
        {
            "module_name": "17_215",
            "app": "17",
            "id_resource": 110
        },
        {
            "module_name": "17_215",
            "app": "17",
            "id_resource": 49
        },
        {
            "module_name": "17_215",
            "app": "17",
            "id_resource": 137
        },
        {
            "module_name": "17_216",
            "app": "17",
            "id_resource": 35
        },
        {
            "module_name": "17_217",
            "app": "17",
            "id_resource": 83
        },
        {
            "module_name": "18_219",
            "app": "18",
            "id_resource": 62
        },
        {
            "module_name": "18_219",
            "app": "18",
            "id_resource": 68
        },
        {
            "module_name": "18_220",
            "app": "18",
            "id_resource": 96
        },
        {
            "module_name": "18_220",
            "app": "18",
            "id_resource": 33
        },
        {
            "module_name": "18_221",
            "app": "18",
            "id_resource": 35
        },
        {
            "module_name": "18_222",
            "app": "18",
            "id_resource": 141
        },
        {
            "module_name": "18_223",
            "app": "18",
            "id_resource": 4
        },
        {
            "module_name": "18_223",
            "app": "18",
            "id_resource": 49
        },
        {
            "module_name": "18_224",
            "app": "18",
            "id_resource": 1
        },
        {
            "module_name": "18_224",
            "app": "18",
            "id_resource": 84
        },
        {
            "module_name": "18_225",
            "app": "18",
            "id_resource": 45
        },
        {
            "module_name": "18_226",
            "app": "18",
            "id_resource": 9
        },
        {
            "module_name": "18_227",
            "app": "18",
            "id_resource": 14
        },
        {
            "module_name": "18_227",
            "app": "18",
            "id_resource": 179
        },
        {
            "module_name": "18_228",
            "app": "18",
            "id_resource": 14
        },
        {
            "module_name": "18_229",
            "app": "18",
            "id_resource": 65
        },
        {
            "module_name": "18_230",
            "app": "18",
            "id_resource": 188
        },
        {
            "module_name": "18_230",
            "app": "18",
            "id_resource": 170
        },
        {
            "module_name": "18_230",
            "app": "18",
            "id_resource": 195
        },
        {
            "module_name": "18_231",
            "app": "18",
            "id_resource": 67
        },
        {
            "module_name": "18_231",
            "app": "18",
            "id_resource": 164
        },
        {
            "module_name": "18_232",
            "app": "18",
            "id_resource": 81
        },
        {
            "module_name": "18_233",
            "app": "18",
            "id_resource": 4
        },
        {
            "module_name": "18_233",
            "app": "18",
            "id_resource": 29
        },
        {
            "module_name": "18_233",
            "app": "18",
            "id_resource": 101
        },
        {
            "module_name": "18_233",
            "app": "18",
            "id_resource": 9
        },
        {
            "module_name": "18_233",
            "app": "18",
            "id_resource": 66
        },
        {
            "module_name": "18_233",
            "app": "18",
            "id_resource": 162
        },
        {
            "module_name": "18_234",
            "app": "18",
            "id_resource": 55
        },
        {
            "module_name": "18_234",
            "app": "18",
            "id_resource": 194
        },
        {
            "module_name": "19_235",
            "app": "19",
            "id_resource": 199
        },
        {
            "module_name": "19_236",
            "app": "19",
            "id_resource": 47
        },
        {
            "module_name": "19_236",
            "app": "19",
            "id_resource": 130
        },
        {
            "module_name": "19_237",
            "app": "19",
            "id_resource": 102
        },
        {
            "module_name": "19_237",
            "app": "19",
            "id_resource": 147
        },
        {
            "module_name": "0_0",
            "app": "0",
            "id_resource": 197
        },
        {
            "module_name": "1_19",
            "app": "1",
            "id_resource": 193
        },
        {
            "module_name": "2_38",
            "app": "2",
            "id_resource": 178
        },
        {
            "module_name": "2_38",
            "app": "2",
            "id_resource": 193
        },
        {
            "module_name": "3_52",
            "app": "3",
            "id_resource": 183
        },
        {
            "module_name": "4_63",
            "app": "4",
            "id_resource": 194
        },
        {
            "module_name": "5_75",
            "app": "5",
            "id_resource": 195
        },
        {
            "module_name": "6_80",
            "app": "6",
            "id_resource": 194
        },
        {
            "module_name": "7_98",
            "app": "7",
            "id_resource": 194
        },
        {
            "module_name": "8_114",
            "app": "8",
            "id_resource": 187
        },
        {
            "module_name": "8_114",
            "app": "8",
            "id_resource": 195
        },
        {
            "module_name": "9_128",
            "app": "9",
            "id_resource": 197
        },
        {
            "module_name": "9_128",
            "app": "9",
            "id_resource": 195
        },
        {
            "module_name": "11_145",
            "app": "11",
            "id_resource": 187
        },
        {
            "module_name": "12_149",
            "app": "12",
            "id_resource": 184
        },
        {
            "module_name": "12_149",
            "app": "12",
            "id_resource": 181
        },
        {
            "module_name": "12_149",
            "app": "12",
            "id_resource": 195
        },
        {
            "module_name": "13_168",
            "app": "13",
            "id_resource": 187
        },
        {
            "module_name": "13_168",
            "app": "13",
            "id_resource": 169
        },
        {
            "module_name": "14_176",
            "app": "14",
            "id_resource": 195
        },
        {
            "module_name": "16_207",
            "app": "16",
            "id_resource": 181
        },
        {
            "module_name": "16_207",
            "app": "16",
            "id_resource": 193
        },
        {
            "module_name": "17_211",
            "app": "17",
            "id_resource": 169
        },
        {
            "module_name": "18_218",
            "app": "18",
            "id_resource": 193
        },
        {
            "module_name": "19_235",
            "app": "19",
            "id_resource": 194
        }
    ]
}